imgfixer-0.1.9.dist-info/METADATA
imgfixer-0.1.9.dist-info/WHEEL
imgfixer-0.1.9.dist-info/entry_points.txt
imgfixer-0.1.9.dist-info/licenses/LICENSE
imgfixer/__init__.py
imgfixer/main.py
imgfixer/static/favicon.ico
imgfixer/static/startup.txt
imgfixer/static/styles.css
imgfixer/templates/index.html
imgfixer/templates/result.html
imgfixer-0.1.9.dist-info/RECORD
