Metadata-Version: 2.1
Name: imgfixer
Version: 0.1.9
Summary: ImgFixer is a tool for fixing image extensions in a directory.
Keywords: image,fix,file extension,rename,automation
Author-Email: Krishnakanth Allika <wheat-chop-octane@duck.com>
Classifier: Development Status :: 4 - Beta
Classifier: Topic :: Utilities
Classifier: License :: OSI Approved :: GNU General Public License v3 (GPLv3)
Classifier: Programming Language :: Python :: 3
Classifier: Programming Language :: Python :: 3.9
Classifier: Programming Language :: Python :: 3.10
Classifier: Programming Language :: Python :: 3.11
Classifier: Programming Language :: Python :: 3.12
Classifier: Programming Language :: Python :: 3.13
Project-URL: Homepage, https://go.allika.eu.org/imgfixerhome
Project-URL: Repository, https://go.allika.eu.org/imgfixerrepo
Project-URL: Documentation, https://go.allika.eu.org/imgfixerdocs
Requires-Python: <=3.14,>=3.9
Requires-Dist: fastapi>=0.115.11
Requires-Dist: filetype>=1.2.0
Requires-Dist: jinja2>=3.1.6
Requires-Dist: python-multipart>=0.0.20
Requires-Dist: uvicorn>=0.34.0
Provides-Extra: dev
Requires-Dist: pytest; extra == "dev"
Requires-Dist: black; extra == "dev"
Requires-Dist: isort; extra == "dev"
Provides-Extra: docs
Requires-Dist: mkdocs; extra == "docs"
Requires-Dist: mkdocs-material; extra == "docs"
